vmecpp-0.4.11.dist-info/RECORD
vmecpp-0.4.11.dist-info/WHEEL
vmecpp-0.4.11.dist-info/entry_points.txt
vmecpp-0.4.11.dist-info/METADATA
vmecpp-0.4.11.dist-info/licenses/LICENSE.txt
include/eigen3/signature_of_eigen3_matrix_library
include/eigen3/unsupported/Eigen/MatrixFunctions
include/eigen3/unsupported/Eigen/AdolcForward
include/eigen3/unsupported/Eigen/AlignedVector3
include/eigen3/unsupported/Eigen/OpenGLSupport
include/eigen3/unsupported/Eigen/LevenbergMarquardt
include/eigen3/unsupported/Eigen/AutoDiff
include/eigen3/unsupported/Eigen/NumericalDiff
include/eigen3/unsupported/Eigen/NonLinearOptimization
include/eigen3/unsupported/Eigen/ArpackSupport
include/eigen3/unsupported/Eigen/Skyline
include/eigen3/unsupported/Eigen/BVH
include/eigen3/unsupported/Eigen/SpecialFunctions
include/eigen3/unsupported/Eigen/Splines
include/eigen3/unsupported/Eigen/KroneckerProduct
include/eigen3/unsupported/Eigen/IterativeSolvers
include/eigen3/unsupported/Eigen/FFT
include/eigen3/unsupported/Eigen/EulerAngles
include/eigen3/unsupported/Eigen/SparseExtra
include/eigen3/unsupported/Eigen/Polynomials
include/eigen3/unsupported/Eigen/MoreVectorization
include/eigen3/unsupported/Eigen/MPRealSupport
include/eigen3/unsupported/Eigen/CXX11/ThreadPool
include/eigen3/unsupported/Eigen/CXX11/TensorSymmetry
include/eigen3/unsupported/Eigen/CXX11/Tensor
include/eigen3/unsupported/Eigen/CXX11/src/util/MaxSizeVector.h
include/eigen3/unsupported/Eigen/CXX11/src/util/CXX11Meta.h
include/eigen3/unsupported/Eigen/CXX11/src/util/CXX11Workarounds.h
include/eigen3/unsupported/Eigen/CXX11/src/util/EmulateArray.h
include/eigen3/unsupported/Eigen/CXX11/src/ThreadPool/ThreadEnvironment.h
include/eigen3/unsupported/Eigen/CXX11/src/ThreadPool/NonBlockingThreadPool.h
include/eigen3/unsupported/Eigen/CXX11/src/ThreadPool/Barrier.h
include/eigen3/unsupported/Eigen/CXX11/src/ThreadPool/ThreadLocal.h
include/eigen3/unsupported/Eigen/CXX11/src/ThreadPool/RunQueue.h
include/eigen3/unsupported/Eigen/CXX11/src/ThreadPool/ThreadPoolInterface.h
include/eigen3/unsupported/Eigen/CXX11/src/ThreadPool/ThreadCancel.h
