Metadata-Version: 2.4
Name: vmecpp
Version: 0.4.11
Summary: Proxima Fusion's reimplementation of the Variational Moments Equilibrium Code (VMEC), a free-boundary ideal-MHD equilibrium solver for stellarators and Tokamaks.
Author-Email: Jonathan Schilling <jons@proximafusion.com>, Enrico Guiraud <eguiraud@proximafusion.com>, Philipp Jurasic <jurasic@proximafusion.com>
License-Expression: MIT
License-File: LICENSE.txt
Classifier: Development Status :: 4 - Beta
Classifier: Operating System :: POSIX :: Linux
Classifier: Operating System :: MacOS :: MacOS X
Classifier: Programming Language :: Python
Classifier: Programming Language :: Python :: 3.10
Classifier: Programming Language :: Python :: 3.11
Classifier: Programming Language :: Python :: 3.12
Classifier: Programming Language :: Python :: 3.13
Classifier: Programming Language :: Python :: Implementation :: CPython
Project-URL: Documentation, https://github.com/proximafusion/vmecpp#readme
Project-URL: Issues, https://github.com/proximafusion/vmecpp/issues
Project-URL: Source, https://github.com/proximafusion/vmecpp
Requires-Python: >=3.10
Requires-Dist: netCDF4<1.7.3
Requires-Dist: numpy
Requires-Dist: pydantic>=2.11
Requires-Dist: jaxtyping>=0.2.6
Requires-Dist: jax!=0.5.2
Requires-Dist: jax!=0.5.1
Requires-Dist: simsopt>=1.8.1
Provides-Extra: test
Requires-Dist: pytest; extra == "test"
Provides-Extra: docs
Requires-Dist: furo; extra == "docs"
Requires-Dist: myst; extra == "docs"
Requires-Dist: myst_parser>=0.13; extra == "docs"
Requires-Dist: sphinx>=4.0; extra == "docs"
Requires-Dist: sphinx-copybutton; extra == "docs"
Requires-Dist: sphinx-autodoc-typehints; extra == "docs"
